MomentoAI/__init__.py
MomentoAI/async_client.py
MomentoAI/client.py
MomentoAI/endpoints.py
MomentoAI/exceptions.py
MomentoAI/utils.py
momentoai-0.1.2.dist-info/licenses/LICENSE
momentoai-0.1.2.dist-info/METADATA
momentoai-0.1.2.dist-info/WHEEL
momentoai-0.1.2.dist-info/top_level.txt
momentoai-0.1.2.dist-info/RECORD
