Metadata-Version: 2.4
Name: momentoai
Version: 0.1.2
Summary: Python SDK for Momento AI — image vectorization, face search, and CLIP embeddings with user-supplied Supabase credentials.
Author-email: Manil Modi <msmodi1701@gmail.com>
License: MIT
Project-URL: Homepage, https://github.com/ManilModi/MomentoAI-SDK
Project-URL: Documentation, https://github.com/ManilModi/MomentoAI-SDK#readme
Requires-Python: >=3.8
License-File: LICENSE
Requires-Dist: httpx>=0.24.1
Requires-Dist: typing-extensions
Dynamic: license-file
